svcmangle/__init__.py
svcmangle/cli.py
svcmangle-0.1.11.dist-info/entry_points.txt
svcmangle-0.1.11.dist-info/WHEEL
svcmangle-0.1.11.dist-info/METADATA
svcmangle-0.1.11.dist-info/RECORD
